{
    "backend": "django",
    "db_name": "",
    "db_pass": "",
    "db_type": "sqlite",
    "db_user": "",
    "dbms": "1",
    "description": "generated product",
    "design": "datta-able",
    "docker": "0",
    "err_code": 0,
    "frontend": "",
    "github_repo": "https://github.com/appseed-projects/0371dd30-b70a-4d7f-82fc-bfe0a1f2429c",
    "heroku": "0",
    "pattern": "mvc",
    "pro": "0",
    "task_id": "0371dd30-b70a-4d7f-82fc-bfe0a1f2429c",
    "task_info": "Upload Sources [0%] - 154 files",
    "task_output": "0371dd30-b70a-4d7f-82fc-bfe0a1f2429c.zip",
    "task_result": "SUCCESS",
    "task_state": "RUNNING",
    "task_ts_end": "2022-06-09-20-38-07",
    "task_ts_start": "2022-06-09-20-38-05"
}